{
    "lexicon": 1,
    "id": "network.habitat.internal.grantPermission",
    "defs": {
        "main": {
            "type": "procedure",
            "description": "Grant permission to a DID using a signed proof.",
            "parameters": {
                "type": "object",
                "required": [
                    "did"
                ],
                "properties": {
                    "did": {
                        "type": "string",
                        "format": "did",
                        "description": "The DID to grant permission to (URL parameter)."
                    }
                }
            },
            "input": {
                "encoding": "application/json",
                "schema": {
                    "type": "object",
                    "required": [
                        "proof"
                    ],
                    "properties": {
                        "proof": {
                            "type": "string",
                            "description": "Signed proof authorizing the permission grant, which can be independently verified by the receiver."
                        }
                    }
                }
            },
            "output": {
                "encoding": "application/json",
                "schema": {
                    "type": "object",
                    "properties": {
                        "status": {
                            "type": "string",
                            "description": "Result status of the permission grant, e.g., 'success' or 'error'."
                        },
                        "message": {
                            "type": "string",
                            "description": "Optional message providing more details about the operation."
                        }
                    }
                }
            }
        }
    }
}